autodiff/Graph.py
autodiff/Tensor.py
autodiff/__init__.py
autodiff/gradients.py
autodiff/nodes/Const.py
autodiff/nodes/Node.py
autodiff/nodes/Operator.py
autodiff/nodes/Var.py
autodiff/nodes/__init__.py
python_autodiff-0.1.1.dist-info/METADATA
python_autodiff-0.1.1.dist-info/WHEEL
python_autodiff-0.1.1.dist-info/top_level.txt
python_autodiff-0.1.1.dist-info/RECORD
