Metadata-Version: 2.4
Name: python-autodiff
Version: 0.1.1
Summary: A simple automatic differentiation library
Home-page: https://github.com/OmPanchal/Autodiff
Author: Om Panchal
Author-email: om.panchal2022@gmail.com
Maintainer: Om Panchal
Maintainer-email: om.panchal2022@gmail.com
Classifier: Programming Language :: Python :: 3
Classifier: Topic :: Scientific/Engineering :: Mathematics
Classifier: License :: OSI Approved :: MIT License
Requires-Dist: numpy
Dynamic: author
Dynamic: author-email
Dynamic: classifier
Dynamic: description
Dynamic: description-content-type
Dynamic: home-page
Dynamic: maintainer
Dynamic: maintainer-email
Dynamic: requires-dist
Dynamic: summary
